{"Albany County":{"2010":[{"state_fips":"56","county":"Albany County","year":2010,"NHWhite":29805,"Black":409,"AmIndian":186,"Asian":947,"NHPI":44,"NHMulti":557,"Hispanic":2959}],"2020":[{"state_fips":"56","county":"Albany County","year":2020,"NHWhite":31709,"Black":383,"AmIndian":283,"Asian":1232,"NHPI":33,"NHMulti":1237,"Hispanic":3740}]},"Big Horn County":{"2010":[{"state_fips":"56","county":"Big Horn County","year":2010,"NHWhite":10289,"Black":8,"AmIndian":135,"Asian":38,"NHPI":4,"NHMulti":112,"Hispanic":862}],"2020":[{"state_fips":"56","county":"Big Horn County","year":2020,"NHWhite":10333,"Black":41,"AmIndian":58,"Asian":70,"NHPI":14,"NHMulti":196,"Hispanic":1082}]},"Campbell County":{"2010":[{"state_fips":"56","county":"Campbell County","year":2010,"NHWhite":38811,"Black":224,"AmIndian":319,"Asian":314,"NHPI":41,"NHMulti":480,"Hispanic":2922}],"2020":[{"state_fips":"56","county":"Campbell County","year":2020,"NHWhite":40986,"Black":364,"AmIndian":209,"Asian":68,"NHPI":29,"NHMulti":1275,"Hispanic":4017}]},"Carbon County":{"2010":[{"state_fips":"56","county":"Carbon County","year":2010,"NHWhite":12614,"Black":179,"AmIndian":116,"Asian":115,"NHPI":6,"NHMulti":148,"Hispanic":2424}],"2020":[{"state_fips":"56","county":"Carbon County","year":2020,"NHWhite":11610,"Black":163,"AmIndian":177,"Asian":116,"NHPI":5,"NHMulti":212,"Hispanic":2780}]},"Converse County":{"2010":[{"state_fips":"56","county":"Converse County","year":2010,"NHWhite":12262,"Black":37,"AmIndian":122,"Asian":0,"NHPI":9,"NHMulti":217,"Hispanic":757}],"2020":[{"state_fips":"56","county":"Converse County","year":2020,"NHWhite":12258,"Black":0,"AmIndian":22,"Asian":19,"NHPI":0,"NHMulti":399,"Hispanic":1144}]},"Crook County":{"2010":[{"state_fips":"56","county":"Crook County","year":2010,"NHWhite":6603,"Black":0,"AmIndian":11,"Asian":6,"NHPI":3,"NHMulti":6,"Hispanic":132}],"2020":[{"state_fips":"56","county":"Crook County","year":2020,"NHWhite":7054,"Black":0,"AmIndian":81,"Asian":18,"NHPI":0,"NHMulti":167,"Hispanic":182}]},"Fremont County":{"2010":[{"state_fips":"56","county":"Fremont County","year":2010,"NHWhite":27902,"Black":143,"AmIndian":7704,"Asian":201,"NHPI":4,"NHMulti":777,"Hispanic":2127}],"2020":[{"state_fips":"56","county":"Fremont County","year":2020,"NHWhite":27549,"Black":182,"AmIndian":7795,"Asian":88,"NHPI":26,"NHMulti":1147,"Hispanic":2914}]},"Goshen County":{"2010":[{"state_fips":"56","county":"Goshen County","year":2010,"NHWhite":11335,"Black":26,"AmIndian":175,"Asian":53,"NHPI":7,"NHMulti":111,"Hispanic":1137}],"2020":[{"state_fips":"56","county":"Goshen County","year":2020,"NHWhite":11289,"Black":42,"AmIndian":110,"Asian":113,"NHPI":15,"NHMulti":184,"Hispanic":1438}]},"Hot Springs County":{"2010":[{"state_fips":"56","county":"Hot Springs County","year":2010,"NHWhite":4585,"Black":0,"AmIndian":38,"Asian":0,"NHPI":0,"NHMulti":54,"Hispanic":43}],"2020":[{"state_fips":"56","county":"Hot Springs County","year":2020,"NHWhite":4185,"Black":0,"AmIndian":118,"Asian":0,"NHPI":0,"NHMulti":56,"Hispanic":143}]},"Johnson County":{"2010":[{"state_fips":"56","county":"Johnson County","year":2010,"NHWhite":7846,"Black":0,"AmIndian":5,"Asian":67,"NHPI":0,"NHMulti":135,"Hispanic":235}],"2020":[{"state_fips":"56","county":"Johnson County","year":2020,"NHWhite":7773,"Black":49,"AmIndian":87,"Asian":129,"NHPI":0,"NHMulti":68,"Hispanic":412}]},"Laramie County":{"2010":[{"state_fips":"56","county":"Laramie County","year":2010,"NHWhite":72579,"Black":2105,"AmIndian":710,"Asian":841,"NHPI":97,"NHMulti":1599,"Hispanic":11280}],"2020":[{"state_fips":"56","county":"Laramie County","year":2020,"NHWhite":77541,"Black":1641,"AmIndian":619,"Asian":1120,"NHPI":87,"NHMulti":3157,"Hispanic":14982}]},"Lincoln County":{"2010":[{"state_fips":"56","county":"Lincoln County","year":2010,"NHWhite":16395,"Black":5,"AmIndian":99,"Asian":59,"NHPI":0,"NHMulti":244,"Hispanic":645}],"2020":[{"state_fips":"56","county":"Lincoln County","year":2020,"NHWhite":18047,"Black":10,"AmIndian":57,"Asian":69,"NHPI":0,"NHMulti":535,"Hispanic":922}]},"Natrona County":{"2010":[{"state_fips":"56","county":"Natrona County","year":2010,"NHWhite":65704,"Black":539,"AmIndian":467,"Asian":525,"NHPI":0,"NHMulti":1325,"Hispanic":4822}],"2020":[{"state_fips":"56","county":"Natrona County","year":2020,"NHWhite":69291,"Black":821,"AmIndian":700,"Asian":435,"NHPI":34,"NHMulti":1795,"Hispanic":6958}]},"Niobrara County":{"2010":[{"state_fips":"56","county":"Niobrara County","year":2010,"NHWhite":2187,"Black":21,"AmIndian":29,"Asian":0,"NHPI":0,"NHMulti":59,"Hispanic":134}],"2020":[{"state_fips":"56","county":"Niobrara County","year":2020,"NHWhite":2077,"Black":18,"AmIndian":43,"Asian":0,"NHPI":35,"NHMulti":55,"Hispanic":149}]},"Park County":{"2010":[{"state_fips":"56","county":"Park County","year":2010,"NHWhite":25616,"Black":38,"AmIndian":262,"Asian":127,"NHPI":19,"NHMulti":224,"Hispanic":1288}],"2020":[{"state_fips":"56","county":"Park County","year":2020,"NHWhite":26532,"Black":206,"AmIndian":52,"Asian":177,"NHPI":0,"NHMulti":532,"Hispanic":1663}]},"Platte County":{"2010":[{"state_fips":"56","county":"Platte County","year":2010,"NHWhite":8077,"Black":0,"AmIndian":43,"Asian":0,"NHPI":0,"NHMulti":30,"Hispanic":505}],"2020":[{"state_fips":"56","county":"Platte County","year":2020,"NHWhite":7365,"Black":5,"AmIndian":0,"Asian":58,"NHPI":50,"NHMulti":380,"Hispanic":714}]},"Sheridan County":{"2010":[{"state_fips":"56","county":"Sheridan County","year":2010,"NHWhite":26390,"Black":13,"AmIndian":374,"Asian":160,"NHPI":0,"NHMulti":431,"Hispanic":956}],"2020":[{"state_fips":"56","county":"Sheridan County","year":2020,"NHWhite":27780,"Black":43,"AmIndian":523,"Asian":223,"NHPI":0,"NHMulti":451,"Hispanic":1329}]},"Sublette County":{"2010":[{"state_fips":"56","county":"Sublette County","year":2010,"NHWhite":7546,"Black":2,"AmIndian":91,"Asian":52,"NHPI":0,"NHMulti":467,"Hispanic":1164}],"2020":[{"state_fips":"56","county":"Sublette County","year":2020,"NHWhite":8748,"Black":1,"AmIndian":30,"Asian":1,"NHPI":0,"NHMulti":362,"Hispanic":723}]},"Sweetwater County":{"2010":[{"state_fips":"56","county":"Sweetwater County","year":2010,"NHWhite":34740,"Black":111,"AmIndian":80,"Asian":232,"NHPI":5,"NHMulti":1211,"Hispanic":5849}],"2020":[{"state_fips":"56","county":"Sweetwater County","year":2020,"NHWhite":34147,"Black":473,"AmIndian":423,"Asian":324,"NHPI":17,"NHMulti":965,"Hispanic":6917}]},"Teton County":{"2010":[{"state_fips":"56","county":"Teton County","year":2010,"NHWhite":17499,"Black":41,"AmIndian":99,"Asian":193,"NHPI":0,"NHMulti":263,"Hispanic":2697}],"2020":[{"state_fips":"56","county":"Teton County","year":2020,"NHWhite":18969,"Black":170,"AmIndian":38,"Asian":334,"NHPI":19,"NHMulti":237,"Hispanic":3449}]},"Uinta County":{"2010":[{"state_fips":"56","county":"Uinta County","year":2010,"NHWhite":18328,"Black":5,"AmIndian":80,"Asian":23,"NHPI":0,"NHMulti":465,"Hispanic":1636}],"2020":[{"state_fips":"56","county":"Uinta County","year":2020,"NHWhite":17793,"Black":55,"AmIndian":103,"Asian":39,"NHPI":0,"NHMulti":455,"Hispanic":1929}]},"Washakie County":{"2010":[{"state_fips":"56","county":"Washakie County","year":2010,"NHWhite":6966,"Black":47,"AmIndian":48,"Asian":60,"NHPI":0,"NHMulti":137,"Hispanic":1013}],"2020":[{"state_fips":"56","county":"Washakie County","year":2020,"NHWhite":6487,"Black":1,"AmIndian":28,"Asian":0,"NHPI":0,"NHMulti":251,"Hispanic":1134}]},"Weston County":{"2010":[{"state_fips":"56","county":"Weston County","year":2010,"NHWhite":6653,"Black":4,"AmIndian":44,"Asian":60,"NHPI":3,"NHMulti":103,"Hispanic":195}],"2020":[{"state_fips":"56","county":"Weston County","year":2020,"NHWhite":6293,"Black":44,"AmIndian":40,"Asian":113,"NHPI":118,"NHMulti":201,"Hispanic":133}]}}
